matplotlib_ai/__init__.py
matplotlib_ai/matplotlib_ai.py
matplotlib_ai-1.0.3.dist-info/LICENSE
matplotlib_ai-1.0.3.dist-info/METADATA
matplotlib_ai-1.0.3.dist-info/WHEEL
matplotlib_ai-1.0.3.dist-info/top_level.txt
matplotlib_ai-1.0.3.dist-info/RECORD
