Metadata-Version: 2.1
Name: matplotlib_ai
Version: 1.0.3
Summary: A GPT-powered tool to bring no-code data visualization to life!
Home-page: https://github.com/notY0rick/mpl_ai
Author: Yorick Chern
Author-email: yorichek.007@gmail.com
License: MIT
Keywords: python,gpt,matplotlib,no code,LLM
Platform: UNKNOWN
License-File: LICENSE
